gtlaunch/main.py
gtlaunch/launcher.py
gtlaunch/__init__.py
gtlaunch-0.2.dist-info/DESCRIPTION.rst
gtlaunch-0.2.dist-info/top_level.txt
gtlaunch-0.2.dist-info/WHEEL
gtlaunch-0.2.dist-info/entry_points.txt
gtlaunch-0.2.dist-info/metadata.json
gtlaunch-0.2.dist-info/METADATA
gtlaunch-0.2.dist-info/RECORD
