Metadata-Version: 2.0
Name: gtlaunch
Version: 0.2
Summary: Gnome Terminal launcher
Home-page: http://github.com/zsiciarz/gtlaunch
Author: Zbigniew Siciarz
Author-email: zbigniew@siciarz.net
License: MIT
Download-URL: http://pypi.python.org/pypi/gtlaunch
Platform: any
Classifier: Development Status :: 4 - Beta
Classifier: Intended Audience :: Developers
Classifier: License :: OSI Approved :: MIT License
Classifier: Operating System :: OS Independent
Classifier: Programming Language :: Python
Classifier: Programming Language :: Python :: 2
Classifier: Programming Language :: Python :: 2.7
Classifier: Programming Language :: Python :: 3
Classifier: Programming Language :: Python :: 3.3
Classifier: Programming Language :: Python :: 3.4
Classifier: Topic :: Utilities
